oculist/__init__.py
oculist/py.typed
oculist-0.0.0.dist-info/METADATA
oculist-0.0.0.dist-info/WHEEL
oculist-0.0.0.dist-info/RECORD
