Metadata-Version: 2.1
Name: oculist
Version: 0.0.0
Summary: \
Author: suned
Author-email: sd@dybro-debel.dk
Requires-Python: >=3.9,<4.0
Classifier: Programming Language :: Python :: 3
Classifier: Programming Language :: Python :: 3.9
Classifier: Programming Language :: Python :: 3.10
Classifier: Programming Language :: Python :: 3.11
